[
  {
    "cause": "Planned Outage",
    "city": "South Seattle",
    "etrTime": 1779067800000,
    "id": 2098775,
    "identifier": "216498",
    "lastUpdatedTime": 1779035525000,
    "latitude": 47.53802,
    "longitude": -122.28528,
    "numPeople": 203,
    "polygons": {
      "hasM": false,
      "hasZ": false,
      "rings": [
        [
          [
            -122.28405,
            47.5399
          ],
          [
            -122.28416,
            47.53984
          ],
          [
            -122.28428,
            47.53982
          ],
          [
            -122.2844,
            47.53985
          ],
          [
            -122.28452,
            47.53994
          ],
          [
            -122.28459,
            47.54004
          ],
          [
            -122.28461,
            47.54016
          ],
          [
            -122.28459,
            47.54028
          ],
          [
            -122.28452,
            47.54038
          ],
          [
            -122.28438,
            47.54048
          ],
          [
            -122.28426,
            47.5405
          ],
          [
            -122.28414,
            47.54048
          ],
          [
            -122.284,
            47.54038
          ],
          [
            -122.28393,
            47.54028
          ],
          [
            -122.28391,
            47.54014
          ],
          [
            -122.28395,
            47.54
          ]
        ],
        [
          [
            -122.28403,
            47.53691
          ],
          [
            -122.28423,
            47.537
          ],
          [
            -122.28432,
            47.53718
          ],
          [
            -122.28439,
            47.53772
          ],
          [
            -122.28438,
            47.53812
          ],
          [
            -122.28439,
            47.53815
          ],
          [
            -122.28442,
            47.53827
          ],
          [
            -122.28439,
            47.53839
          ],
          [
            -122.28432,
            47.53849
          ],
          [
            -122.28419,
            47.53858
          ],
          [
            -122.28407,
            47.53861
          ],
          [
            -122.28395,
            47.53858
          ],
          [
            -122.28381,
            47.53849
          ],
          [
            -122.28374,
            47.53839
          ],
          [
            -122.28372,
            47.53825
          ],
          [
            -122.28374,
            47.53817
          ],
          [
            -122.28369,
            47.53776
          ],
          [
            -122.2837,
            47.53714
          ],
          [
            -122.28382,
            47.53697
          ]
        ],
        [
          [
            -122.28834,
            47.53653
          ],
          [
            -122.28847,
            47.53659
          ],
          [
            -122.28856,
            47.5367
          ],
          [
            -122.28859,
            47.53682
          ],
          [
            -122.28859,
            47.53693
          ],
          [
            -122.28898,
            47.5371
          ],
          [
            -122.28909,
            47.53719
          ],
          [
            -122.28915,
            47.5373
          ],
          [
            -122.28916,
            47.53739
          ],
          [
            -122.28927,
            47.5374
          ],
          [
            -122.28944,
            47.53754
          ],
          [
            -122.28948,
            47.53766
          ],
          [
            -122.28948,
            47.53795
          ],
          [
            -122.28944,
            47.53806
          ],
          [
            -122.28933,
            47.53816
          ],
          [
            -122.2892,
            47.5382
          ],
          [
            -122.28906,
            47.53818
          ],
          [
            -122.28866,
            47.53792
          ],
          [
            -122.28858,
            47.53783
          ],
          [
            -122.28858,
            47.53781
          ],
          [
            -122.28835,
            47.5378
          ],
          [
            -122.28822,
            47.53776
          ],
          [
            -122.28812,
            47.53768
          ],
          [
            -122.28797,
            47.53722
          ],
          [
            -122.28797,
            47.53722
          ],
          [
            -122.28777,
            47.53714
          ],
          [
            -122.28768,
            47.537
          ],
          [
            -122.28767,
            47.53684
          ],
          [
            -122.28773,
            47.53671
          ],
          [
            -122.28784,
            47.53662
          ],
          [
            -122.28821,
            47.53653
          ]
        ],
        [
          [
            -122.28495,
            47.53651
          ],
          [
            -122.28507,
            47.53654
          ],
          [
            -122.28507,
            47.53654
          ],
          [
            -122.28509,
            47.53653
          ],
          [
            -122.28567,
            47.53652
          ],
          [
            -122.28611,
            47.53658
          ],
          [
            -122.28627,
            47.53673
          ],
          [
            -122.2863,
            47.53693
          ],
          [
            -122.28618,
            47.53712
          ],
          [
            -122.28598,
            47.53718
          ],
          [
            -122.28589,
            47.53718
          ],
          [
            -122.28594,
            47.53725
          ],
          [
            -122.28595,
            47.53737
          ],
          [
            -122.28593,
            47.53746
          ],
          [
            -122.28595,
            47.53749
          ],
          [
            -122.28597,
            47.53761
          ],
          [
            -122.28594,
            47.53773
          ],
          [
            -122.28592,
            47.53775
          ],
          [
            -122.28596,
            47.53781
          ],
          [
            -122.28597,
            47.53793
          ],
          [
            -122.28594,
            47.53803
          ],
          [
            -122.28597,
            47.53822
          ],
          [
            -122.28587,
            47.53839
          ],
          [
            -122.28569,
            47.53847
          ],
          [
            -122.28539,
            47.5385
          ],
          [
            -122.28545,
            47.53859
          ],
          [
            -122.28547,
            47.53871
          ],
          [
            -122.28545,
            47.53883
          ],
          [
            -122.28538,
            47.53893
          ],
          [
            -122.28524,
            47.53903
          ],
          [
            -122.28512,
            47.53905
          ],
          [
            -122.28511,
            47.53905
          ],
          [
            -122.28532,
            47.53926
          ],
          [
            -122.28563,
            47.53968
          ],
          [
            -122.28566,
            47.5398
          ],
          [
            -122.28563,
            47.53992
          ],
          [
            -122.28557,
            47.54002
          ],
          [
            -122.28546,
            47.54009
          ],
          [
            -122.2853,
            47.54011
          ],
          [
            -122.28514,
            47.54003
          ],
          [
            -122.28478,
            47.53967
          ],
          [
            -122.28446,
            47.53926
          ],
          [
            -122.28445,
            47.53906
          ],
          [
            -122.28458,
            47.53888
          ],
          [
            -122.28478,
            47.53883
          ],
          [
            -122.2848,
            47.53884
          ],
          [
            -122.28479,
            47.53883
          ],
          [
            -122.28477,
            47.53869
          ],
          [
            -122.28481,
            47.53855
          ],
          [
            -122.28491,
            47.53845
          ],
          [
            -122.28493,
            47.53844
          ],
          [
            -122.28484,
            47.53838
          ],
          [
            -122.28478,
            47.53827
          ],
          [
            -122.28476,
            47.53815
          ],
          [
            -122.28479,
            47.53805
          ],
          [
            -122.28478,
            47.53805
          ],
          [
            -122.28476,
            47.53785
          ],
          [
            -122.28481,
            47.53776
          ],
          [
            -122.28478,
            47.53773
          ],
          [
            -122.28475,
            47.53753
          ],
          [
            -122.28478,
            47.53749
          ],
          [
            -122.28475,
            47.5373
          ],
          [
            -122.28483,
            47.53716
          ],
          [
            -122.28481,
            47.53716
          ],
          [
            -122.28467,
            47.53707
          ],
          [
            -122.2846,
            47.53697
          ],
          [
            -122.28458,
            47.53682
          ],
          [
            -122.28462,
            47.53669
          ],
          [
            -122.28472,
            47.53658
          ],
          [
            -122.28483,
            47.53652
          ]
        ]
      ],
      "spatialReference": {
        "latestWkid": 4326,
        "wkid": 4326
      },
      "type": "polygon"
    },
    "startTime": 1779035343000,
    "state": "WA",
    "status": "Dispatched",
    "title": "Planned Outage",
    "type": "PLANNED_OUTAGE"
  }
]