[
  {
    "cause": "Equipment Failure",
    "city": "South Seattle",
    "etrTime": 1777688820000,
    "id": 2091741,
    "identifier": "215585",
    "lastUpdatedTime": 1777678083000,
    "latitude": 47.56697,
    "longitude": -122.2881,
    "numPeople": 1,
    "polygons": {
      "hasM": false,
      "hasZ": false,
      "rings": [
        [
          [
            -122.28799,
            47.56675
          ],
          [
            -122.2881,
            47.56669
          ],
          [
            -122.28822,
            47.56668
          ],
          [
            -122.28834,
            47.56671
          ],
          [
            -122.28846,
            47.56679
          ],
          [
            -122.28853,
            47.56689
          ],
          [
            -122.28855,
            47.56701
          ],
          [
            -122.28853,
            47.56713
          ],
          [
            -122.28846,
            47.56724
          ],
          [
            -122.28832,
            47.56733
          ],
          [
            -122.2882,
            47.56735
          ],
          [
            -122.28808,
            47.56733
          ],
          [
            -122.28794,
            47.56724
          ],
          [
            -122.28788,
            47.56713
          ],
          [
            -122.28785,
            47.56699
          ],
          [
            -122.28789,
            47.56686
          ]
        ]
      ],
      "spatialReference": {
        "latestWkid": 4326,
        "wkid": 4326
      },
      "type": "polygon"
    },
    "startTime": 1777641864000,
    "state": "WA",
    "status": "Dispatched",
    "title": "Outage"
  },
  {
    "cause": "Investigating",
    "city": "South Seattle",
    "id": 2091939,
    "identifier": "215619",
    "lastUpdatedTime": 1777679282000,
    "latitude": 47.5315,
    "longitude": -122.35535,
    "numPeople": 1,
    "polygons": {
      "hasM": false,
      "hasZ": false,
      "rings": [
        [
          [
            -122.35519,
            47.53126
          ],
          [
            -122.3553,
            47.5312
          ],
          [
            -122.35542,
            47.53118
          ],
          [
            -122.35554,
            47.53122
          ],
          [
            -122.35566,
            47.5313
          ],
          [
            -122.35573,
            47.5314
          ],
          [
            -122.35575,
            47.53152
          ],
          [
            -122.35573,
            47.53164
          ],
          [
            -122.35566,
            47.53175
          ],
          [
            -122.35552,
            47.53184
          ],
          [
            -122.3554,
            47.53186
          ],
          [
            -122.35528,
            47.53184
          ],
          [
            -122.35514,
            47.53175
          ],
          [
            -122.35507,
            47.53164
          ],
          [
            -122.35505,
            47.5315
          ],
          [
            -122.35509,
            47.53137
          ]
        ]
      ],
      "spatialReference": {
        "latestWkid": 4326,
        "wkid": 4326
      },
      "type": "polygon"
    },
    "startTime": 1777679257000,
    "state": "WA",
    "title": "Outage"
  }
]