[
  {
    "cause": "Equipment Failure",
    "city": "North Seattle",
    "etrTime": 1783119600000,
    "id": 2146967,
    "identifier": "218973",
    "lastUpdatedTime": 1783102684000,
    "latitude": 47.7274,
    "longitude": -122.29521,
    "numPeople": 52,
    "polygons": {
      "hasM": false,
      "hasZ": false,
      "rings": [
        [
          [
            -122.29505,
            47.72716
          ],
          [
            -122.29516,
            47.7271
          ],
          [
            -122.29528,
            47.72708
          ],
          [
            -122.2954,
            47.72711
          ],
          [
            -122.29552,
            47.7272
          ],
          [
            -122.29559,
            47.7273
          ],
          [
            -122.29561,
            47.72742
          ],
          [
            -122.29559,
            47.72754
          ],
          [
            -122.29552,
            47.72764
          ],
          [
            -122.29538,
            47.72773
          ],
          [
            -122.29526,
            47.72776
          ],
          [
            -122.29514,
            47.72773
          ],
          [
            -122.295,
            47.72764
          ],
          [
            -122.29493,
            47.72754
          ],
          [
            -122.29491,
            47.7274
          ],
          [
            -122.29495,
            47.72726
          ]
        ]
      ],
      "spatialReference": {
        "latestWkid": 4326,
        "wkid": 4326
      },
      "type": "polygon"
    },
    "startTime": 1783097386000,
    "state": "WA",
    "status": "Dispatched",
    "title": "Outage"
  },
  {
    "cause": "Investigating",
    "city": "South Seattle",
    "etrTime": 1783137600000,
    "id": 2147015,
    "identifier": "218976",
    "lastUpdatedTime": 1783110965000,
    "latitude": 47.55613,
    "longitude": -122.28524,
    "numPeople": 2,
    "polygons": {
      "hasM": false,
      "hasZ": false,
      "rings": [
        [
          [
            -122.28485,
            47.55621
          ],
          [
            -122.28502,
            47.55595
          ],
          [
            -122.28536,
            47.55564
          ],
          [
            -122.28548,
            47.55561
          ],
          [
            -122.2856,
            47.55564
          ],
          [
            -122.2857,
            47.55571
          ],
          [
            -122.28577,
            47.55581
          ],
          [
            -122.28579,
            47.55595
          ],
          [
            -122.28574,
            47.5561
          ],
          [
            -122.28557,
            47.55636
          ],
          [
            -122.28524,
            47.55667
          ],
          [
            -122.28503,
            47.55669
          ],
          [
            -122.28488,
            47.55659
          ],
          [
            -122.2848,
            47.5564
          ]
        ]
      ],
      "spatialReference": {
        "latestWkid": 4326,
        "wkid": 4326
      },
      "type": "polygon"
    },
    "startTime": 1783104033000,
    "state": "WA",
    "status": "Dispatched",
    "title": "Outage"
  },
  {
    "cause": "Investigating",
    "city": "South Seattle",
    "etrTime": 1783127780000,
    "id": 2147029,
    "identifier": "218977",
    "lastUpdatedTime": 1783106764000,
    "latitude": 47.55619,
    "longitude": -122.31069,
    "numPeople": 2,
    "polygons": {
      "hasM": false,
      "hasZ": false,
      "rings": [
        [
          [
            -122.31058,
            47.55596
          ],
          [
            -122.31069,
            47.5559
          ],
          [
            -122.31081,
            47.55589
          ],
          [
            -122.31093,
            47.55592
          ],
          [
            -122.31105,
            47.556
          ],
          [
            -122.31112,
            47.5561
          ],
          [
            -122.31114,
            47.55622
          ],
          [
            -122.31112,
            47.55635
          ],
          [
            -122.31105,
            47.55645
          ],
          [
            -122.31091,
            47.55654
          ],
          [
            -122.31079,
            47.55656
          ],
          [
            -122.31067,
            47.55654
          ],
          [
            -122.31053,
            47.55645
          ],
          [
            -122.31046,
            47.55635
          ],
          [
            -122.31044,
            47.5562
          ],
          [
            -122.31048,
            47.55607
          ]
        ]
      ],
      "spatialReference": {
        "latestWkid": 4326,
        "wkid": 4326
      },
      "type": "polygon"
    },
    "startTime": 1783105633000,
    "state": "WA",
    "status": "Dispatched",
    "title": "Outage"
  },
  {
    "cause": "Investigating",
    "city": "South Seattle",
    "etrTime": 1783134080000,
    "id": 2147156,
    "identifier": "218981",
    "lastUpdatedTime": 1783116003000,
    "latitude": 47.60757,
    "longitude": -122.32408,
    "numPeople": 1,
    "polygons": {
      "hasM": false,
      "hasZ": false,
      "rings": [
        [
          [
            -122.32382,
            47.60729
          ],
          [
            -122.32393,
            47.60722
          ],
          [
            -122.32405,
            47.60721
          ],
          [
            -122.32417,
            47.60724
          ],
          [
            -122.32429,
            47.60732
          ],
          [
            -122.32435,
            47.60743
          ],
          [
            -122.32438,
            47.60755
          ],
          [
            -122.32435,
            47.60767
          ],
          [
            -122.32429,
            47.60777
          ],
          [
            -122.32415,
            47.60786
          ],
          [
            -122.32403,
            47.60788
          ],
          [
            -122.32391,
            47.60786
          ],
          [
            -122.32377,
            47.60777
          ],
          [
            -122.3237,
            47.60767
          ],
          [
            -122.32368,
            47.60753
          ],
          [
            -122.32372,
            47.60739
          ]
        ]
      ],
      "spatialReference": {
        "latestWkid": 4326,
        "wkid": 4326
      },
      "type": "polygon"
    },
    "startTime": 1783111833000,
    "state": "WA",
    "status": "Dispatched",
    "title": "Outage"
  }
]