[
  {
    "cause": "Planned Outage",
    "city": "South Seattle",
    "id": 2084724,
    "identifier": "215040",
    "lastUpdatedTime": 1777009563000,
    "latitude": 47.5741,
    "longitude": -122.32833,
    "numPeople": 3,
    "polygons": {
      "hasM": false,
      "hasZ": false,
      "rings": [
        [
          [
            -122.32853,
            47.57498
          ],
          [
            -122.32864,
            47.57492
          ],
          [
            -122.32876,
            47.5749
          ],
          [
            -122.32888,
            47.57494
          ],
          [
            -122.329,
            47.57502
          ],
          [
            -122.32907,
            47.57512
          ],
          [
            -122.32909,
            47.57524
          ],
          [
            -122.32907,
            47.57536
          ],
          [
            -122.329,
            47.57546
          ],
          [
            -122.32886,
            47.57556
          ],
          [
            -122.32874,
            47.57558
          ],
          [
            -122.32862,
            47.57556
          ],
          [
            -122.32848,
            47.57546
          ],
          [
            -122.32842,
            47.57536
          ],
          [
            -122.32839,
            47.57522
          ],
          [
            -122.32843,
            47.57508
          ]
        ],
        [
          [
            -122.32864,
            47.57439
          ],
          [
            -122.32831,
            47.57443
          ],
          [
            -122.32801,
            47.57443
          ],
          [
            -122.3279,
            47.5744
          ],
          [
            -122.3278,
            47.57432
          ],
          [
            -122.32774,
            47.57421
          ],
          [
            -122.32772,
            47.57409
          ],
          [
            -122.32775,
            47.57397
          ],
          [
            -122.32784,
            47.57386
          ],
          [
            -122.32797,
            47.57381
          ],
          [
            -122.32831,
            47.57376
          ],
          [
            -122.32861,
            47.57376
          ],
          [
            -122.32873,
            47.57379
          ],
          [
            -122.32887,
            47.57394
          ],
          [
            -122.3289,
            47.57412
          ],
          [
            -122.32881,
            47.5743
          ]
        ]
      ],
      "spatialReference": {
        "latestWkid": 4326,
        "wkid": 4326
      },
      "type": "polygon"
    },
    "startTime": 1777004250000,
    "state": "WA",
    "status": "Dispatched",
    "title": "Planned Outage",
    "type": "PLANNED_OUTAGE"
  }
]